mushi/__init__.py
mushi/_version.py
mushi/composition.py
mushi/histories.py
mushi/ksfs.py
mushi/loss_functions.py
mushi/optimization.py
mushi/utils.py
mushi-1.1.1.data/scripts/mushi
mushi-1.1.1.dist-info/LICENSE
mushi-1.1.1.dist-info/METADATA
mushi-1.1.1.dist-info/WHEEL
mushi-1.1.1.dist-info/top_level.txt
mushi-1.1.1.dist-info/RECORD
