Metadata-Version: 2.1
Name: mushi
Version: 1.1.1
Summary: 🍄 [mu]tation [s]pectrum [h]istory [i]nference 🍄
Home-page: https://github.com/harrispopgen/mushi
Author: William DeWitt
Author-email: wsdewitt@gmail.com
License: UNKNOWN
Platform: UNKNOWN
Classifier: Programming Language :: Python :: 3
Classifier: License :: OSI Approved :: MIT License
Classifier: Operating System :: OS Independent
Requires-Python: >=3.7.*
License-File: LICENSE
Requires-Dist: jax
Requires-Dist: jaxlib
Requires-Dist: prox-tv-SDIST
Requires-Dist: seaborn
Requires-Dist: pandas
Requires-Dist: matplotlib
Requires-Dist: numpy
Requires-Dist: scipy
